aminofix/__init__.py
aminofix/acm.py
aminofix/client.py
aminofix/socket.py
aminofix/sub_client.py
aminofix/asyncfix/__init__.py
aminofix/asyncfix/acm.py
aminofix/asyncfix/client.py
aminofix/asyncfix/socket.py
aminofix/asyncfix/sub_client.py
aminofix/lib/__init__.py
aminofix/lib/util/__init__.py
aminofix/lib/util/exceptions.py
aminofix/lib/util/headers.py
aminofix/lib/util/helpers.py
aminofix/lib/util/objects.py
amino.fix-2.3.6.1.dist-info/LICENSE
amino.fix-2.3.6.1.dist-info/METADATA
amino.fix-2.3.6.1.dist-info/WHEEL
amino.fix-2.3.6.1.dist-info/top_level.txt
amino.fix-2.3.6.1.dist-info/RECORD
