Metadata-Version: 2.1
Name: amino.fix
Version: 2.3.6.1
Summary: Library for Amino. Discord - https://discord.gg/Bf3dpBRJHj
Home-page: https://github.com/Minori100/Amino.fix
Author: Minori
Author-email: minorigithub@gmail.com
License: MIT
Keywords: aminoapps,amino.fix,amino,amino-bot,narvii,api,python,python3,python3.x,minori
Platform: UNKNOWN
Requires-Python: >=3.6
License-File: LICENSE
Requires-Dist: requests
Requires-Dist: websocket-client (==1.3.1)
Requires-Dist: setuptools
Requires-Dist: json-minify
Requires-Dist: six
Requires-Dist: aiohttp
Requires-Dist: websockets
